lpngram/__init__.py
lpngram/__main__.py
lpngram/ngrams.py
lpngram/smoothing.py
lpngram-0.2.dist-info/AUTHORS.md
lpngram-0.2.dist-info/LICENSE
lpngram-0.2.dist-info/METADATA
lpngram-0.2.dist-info/WHEEL
lpngram-0.2.dist-info/entry_points.txt
lpngram-0.2.dist-info/top_level.txt
lpngram-0.2.dist-info/RECORD
