Metadata-Version: 2.1
Name: lpngram
Version: 0.2
Summary: Python libary for ngram collection and frequency smoothing
Home-page: https://github.com/tresoldi/lpngram
Author: Tiago Tresoldi
Author-email: tiago.tresoldi@lingfil.uu.se
License: MIT
Keywords: ngram,markov,smoothing
Classifier: License :: OSI Approved :: MIT License
Classifier: Operating System :: OS Independent
Classifier: Programming Language :: Python :: 3
Classifier: Topic :: Software Development :: Libraries
Requires-Python: >=3.7
License-File: LICENSE
License-File: AUTHORS.md
Requires-Dist: numpy
Requires-Dist: scipy
